ft_ascii/__init__.py
ft_ascii/count_in_list.py
ft_ascii/splash.py
ft_ascii-1.0.0.dist-info/licenses/LICENSE
ft_ascii-1.0.0.dist-info/METADATA
ft_ascii-1.0.0.dist-info/WHEEL
ft_ascii-1.0.0.dist-info/entry_points.txt
ft_ascii-1.0.0.dist-info/top_level.txt
ft_ascii-1.0.0.dist-info/RECORD
