Metadata-Version: 2.4
Name: ft_ascii
Version: 1.0.0
Summary: A CLI-interface, 42 school themed animated splash screen
Author-email: Paulo Nicolau <paulo.nicolau7@gmail.com>
License-Expression: MIT
Classifier: Programming Language :: Python :: 3
Classifier: Operating System :: OS Independent
Classifier: Development Status :: 6 - Mature
Classifier: Topic :: Games/Entertainment
Requires-Python: >=3.10
License-File: LICENSE
Dynamic: license-file
